ddlparse/__init__.py
ddlparse/ddlparse.py
ddlparse-1.10.0.dist-info/LICENSE.md
ddlparse-1.10.0.dist-info/METADATA
ddlparse-1.10.0.dist-info/WHEEL
ddlparse-1.10.0.dist-info/top_level.txt
ddlparse-1.10.0.dist-info/RECORD
