Metadata-Version: 2.1
Name: ddlparse
Version: 1.10.0
Summary: DDL parase and Convert to BigQuery JSON schema
Home-page: http://github.com/shinichi-takii/ddlparse
Author: Shinichi Takii
Author-email: shinichi.takii@shaketh.com
License: BSD-3-Clause
Keywords: ddl sql parse bigquery
Platform: UNKNOWN
Classifier: Development Status :: 5 - Production/Stable
Classifier: License :: OSI Approved :: BSD License
Classifier: Programming Language :: Python
Classifier: Programming Language :: Python :: 3
Classifier: Programming Language :: Python :: 3.5
Classifier: Programming Language :: Python :: 3.6
Classifier: Programming Language :: Python :: 3.7
Classifier: Programming Language :: Python :: 3.8
Classifier: Programming Language :: Python :: 3.9
Classifier: Topic :: Database
Classifier: Topic :: Software Development :: Libraries :: Python Modules
